{"cameraMode":{"drawMode":0,"name":"Shaded","section":"Shading Mode"},"sceneLighting":true,"audioPlay":false,"sceneViewState":{"m_AlwaysRefresh":false,"showFog":true,"showSkybox":true,"showFlares":true,"showImageEffects":true,"showParticleSystems":true,"showVisualEffectGraphs":true,"m_FxEnabled":true},"in2DMode":false,"pivot":{"x":0.1447165310382843,"y":4.130556106567383,"z":6.927256107330322},"rotation":{"x":-0.03045634552836418,"y":0.6934343576431274,"z":-0.029351290315389634,"w":-0.7192903161048889},"size":3.753239154815674,"orthographic":false}